{
	"info": {
		"_postman_id": "96ca8228-b65f-4129-abd3-9d1a5a4a9370",
		"name": "LMS Program Batch Module",
		"schema": "https://schema.getpostman.com/json/collection/v2.1.0/collection.json",
		"_exporter_id": "50024072",
		"_collection_link": "https://nehak2025-2536606.postman.co/workspace/Neha's-Workspace~bd961bac-afb6-4a46-85fb-ee5e6c14829e/collection/50024072-96ca8228-b65f-4129-abd3-9d1a5a4a9370?action=share&source=collection_link&creator=50024072"
	},
	"item": [
		{
			"name": "Positive Tests",
			"item": [
				{
					"name": "Get All Batches",
					"event": [
						{
							"listen": "test",
							"script": {
								"exec": [
									"pm.test(\"Status code is 200\", function () {",
									"    pm.response.to.have.status(200);",
									"});",
									"const response = pm.response.json();",
									"",
									"// Test for response body structure",
									"pm.test(\"Response is an array\", function () {",
									"    pm.expect(response).to.be.an('array');",
									"});",
									"",
									"// Loop through each batch and check properties",
									"response.forEach(batch => {",
									"    pm.test(`Batch ID ${batch.batchId} has required fields`, function () {",
									"        pm.expect(batch).to.have.all.keys('batchId', 'batchName', 'batchDescription', 'batchStatus', 'batchNoOfClasses', 'programId', 'programName');",
									"    });",
									"});",
									"",
									"const jsonData = pm.response.json();",
									"const batches = jsonData || [];",
									"",
									"// Helper function to generate random letters",
									"function randomLetters(len) {",
									"    const letters = \"ABCDEFGHIJKLMNOPQRSTUVWXYZabcdefghijklmnopqrstuvwxyz\";",
									"    let s = \"\";",
									"    for (let i = 0; i < len; i++) {",
									"        s += letters.charAt(Math.floor(Math.random() * letters.length));",
									"    }",
									"    return s;",
									"}",
									"",
									"// Helper function to generate random numbers (1-99)",
									"function randomBatchNumber() {",
									"    return Math.floor(Math.random() * 99) + 1;",
									"}",
									"",
									"if (batches && batches.length > 0) {",
									"    // Filter active batches",
									"    const activeBatches = batches.filter(batch => ",
									"        batch.batchStatus && batch.batchStatus.toLowerCase() === 'active'",
									"    );",
									"",
									"    if (activeBatches && activeBatches.length > 0) {",
									"        // Sort by batchId",
									"        const sorted = activeBatches.sort((a, b) => a.batchId - b.batchId);",
									"        ",
									"        const timestamp = Date.now();",
									"        ",
									"        // For GET operations - use first batch",
									"        pm.environment.set(\"getBatchId\", sorted[0].batchId);",
									"        pm.environment.set(\"getBatchName\", sorted[0].batchName);",
									"        ",
									"        // For GET by Program ID",
									"        if (sorted[0].programId) {",
									"            pm.environment.set(\"getProgramIdForBatch\", sorted[0].programId);",
									"        }",
									"        ",
									"        // Store program name for creating batch names",
									"        if (sorted[0].programName) {",
									"            pm.environment.set(\"programNameForBatch\", sorted[0].programName);",
									"            const batchSeq = randomBatchNumber();",
									"            pm.environment.set(\"newBatchName\", `${sorted[0].programName}${batchSeq}`);",
									"            batchSeq1 = randomBatchNumber();",
									"            pm.environment.set(\"newBatchName4DescShort\", `${sorted[0].programName}${batchSeq1}`);",
									"            batchSeq2 = randomBatchNumber();",
									"            pm.environment.set(\"newBatchName4DescLong\", `${sorted[0].programName}${batchSeq2}`);",
									"        }",
									"        ",
									"        // For CREATE - generate unique batch data",
									"        pm.environment.set(\"newBatchDescription\", `Batch-${randomLetters(4)}`);",
									"        pm.environment.set(\"newBatchNoOfClasses\", Math.floor(Math.random() * 50) + 10); // 10-59 classes",
									"        pm.environment.set(\"newBatchStatus\", \"Active\");",
									"        pm.environment.set(\"newProgramId\", sorted[0].programId);",
									"        ",
									"        pm.environment.set(\"updatedBatchDescription\", `Updated-${timestamp}`);",
									"         console.log(\"✅ Batch test data setup complete!\");",
									"        console.log(\"Total batches:\", batches.length);",
									"        console.log(\"Active batches:\", activeBatches.length);",
									"        console.log(\"New batch name:\", pm.environment.get(\"newBatchName\"));",
									"    } else {",
									"        console.log(\"⚠️ No active batches found!\");",
									"    }",
									"} else {",
									"    console.log(\"⚠️ No batches returned in response!\");",
									"}",
									"",
									"// Test assertions",
									"pm.test(\"Status code is 200\", function () {",
									"    pm.response.to.have.status(200);",
									"});",
									"",
									"pm.test(\"Response is an array\", function () {",
									"    pm.expect(batches).to.be.an('array');",
									"});",
									"",
									"pm.test(\"Batches contain required fields\", function () {",
									"    if (batches.length > 0) {",
									"        pm.expect(batches[0]).to.have.property('batchId');",
									"        pm.expect(batches[0]).to.have.property('batchName');",
									"        pm.expect(batches[0]).to.have.property('programId');",
									"        pm.expect(batches[0]).to.have.property('batchStatus');",
									"    }",
									"});",
									""
								],
								"type": "text/javascript",
								"packages": {},
								"requests": {}
							}
						}
					],
					"request": {
						"method": "GET",
						"header": [
							{
								"key": "Authorization",
								"value": "Bearer {{authToken}}",
								"type": "text"
							}
						],
						"url": {
							"raw": "{{baseUrl}}/batches",
							"host": [
								"{{baseUrl}}"
							],
							"path": [
								"batches"
							]
						}
					},
					"response": []
				},
				{
					"name": "Get Batch by BatchID",
					"event": [
						{
							"listen": "test",
							"script": {
								"exec": [
									"pm.test(\"Status code is 200\", function () {\r",
									"    pm.response.to.have.status(200);\r",
									"});\r",
									"\r",
									"pm.test(\"Response contains required batch fields\", function () {\r",
									"    const jsonData = pm.response.json();\r",
									"\r",
									"    pm.expect(jsonData).to.have.property(\"batchId\");\r",
									"    pm.expect(jsonData).to.have.property(\"batchName\");\r",
									"    pm.expect(jsonData).to.have.property(\"batchDescription\");\r",
									"    pm.expect(jsonData).to.have.property(\"batchNoOfClasses\");\r",
									"    pm.expect(jsonData).to.have.property(\"batchStatus\");\r",
									"    pm.expect(jsonData).to.have.property(\"programId\");\r",
									"    pm.expect(jsonData).to.have.property(\"programName\");\r",
									"});\r",
									""
								],
								"type": "text/javascript",
								"packages": {},
								"requests": {}
							}
						}
					],
					"request": {
						"method": "GET",
						"header": [
							{
								"key": "Authorization",
								"value": "Bearer {{authToken}}",
								"type": "text"
							}
						],
						"url": {
							"raw": "{{baseUrl}}/batches/batchId/{{getBatchId}}",
							"host": [
								"{{baseUrl}}"
							],
							"path": [
								"batches",
								"batchId",
								"{{getBatchId}}"
							]
						}
					},
					"response": []
				},
				{
					"name": "Get Batch by Batch Name",
					"event": [
						{
							"listen": "test",
							"script": {
								"exec": [
									"pm.test(\"Status code is 200\", function () {\r",
									"    pm.response.to.have.status(200);\r",
									"});\r",
									"\r",
									"const jsonData = pm.response.json();\r",
									"\r",
									"pm.test(\"Response is an array\", function () {\r",
									"    pm.expect(jsonData).to.be.an('array');\r",
									"});\r",
									"\r",
									"pm.test(\"Response contains batches\", function () {\r",
									"    pm.expect(jsonData.length).to.be.greaterThan(0);\r",
									"});\r",
									"\r",
									"// Individual test for each batch\r",
									"jsonData.forEach((batch, index) => {\r",
									"    pm.test(`Batch ${index + 1} (ID: ${batch.batchId}) has all required fields`, function () {\r",
									"        pm.expect(batch).to.have.property(\"batchId\");\r",
									"        pm.expect(batch).to.have.property(\"batchName\");\r",
									"        pm.expect(batch).to.have.property(\"batchDescription\");\r",
									"        pm.expect(batch).to.have.property(\"batchNoOfClasses\");\r",
									"        pm.expect(batch).to.have.property(\"batchStatus\");\r",
									"        pm.expect(batch).to.have.property(\"programId\");\r",
									"        pm.expect(batch).to.have.property(\"programName\");\r",
									"    });\r",
									"});\r",
									""
								],
								"type": "text/javascript",
								"packages": {},
								"requests": {}
							}
						}
					],
					"request": {
						"method": "GET",
						"header": [
							{
								"key": "Authorization",
								"value": "Bearer {{authToken}}",
								"type": "text"
							}
						],
						"url": {
							"raw": "{{baseUrl}}/batches/batchName/{{getBatchName}}",
							"host": [
								"{{baseUrl}}"
							],
							"path": [
								"batches",
								"batchName",
								"{{getBatchName}}"
							]
						}
					},
					"response": []
				},
				{
					"name": "Get Batch by Program ID",
					"event": [
						{
							"listen": "test",
							"script": {
								"exec": [
									"pm.test(\"Status code is 200\", function () {\r",
									"    pm.response.to.have.status(200);\r",
									"});\r",
									"\r",
									"pm.test(\"Response is an array of batches\", function () {\r",
									"    const jsonData = pm.response.json();\r",
									"    pm.expect(jsonData).to.be.an('array');\r",
									"    pm.expect(jsonData.length).to.be.greaterThan(0);\r",
									"});\r",
									"\r",
									"pm.test(\"Each batch contains required fields\", function () {\r",
									"    const jsonData = pm.response.json();\r",
									"    \r",
									"    jsonData.forEach(batch => {\r",
									"        pm.expect(batch).to.have.property(\"batchId\");\r",
									"        pm.expect(batch).to.have.property(\"batchName\");\r",
									"        pm.expect(batch).to.have.property(\"batchDescription\");\r",
									"        pm.expect(batch).to.have.property(\"batchNoOfClasses\");\r",
									"        pm.expect(batch).to.have.property(\"batchStatus\");\r",
									"        pm.expect(batch).to.have.property(\"programId\");\r",
									"        pm.expect(batch).to.have.property(\"programName\");\r",
									"    });\r",
									"});"
								],
								"type": "text/javascript",
								"packages": {},
								"requests": {}
							}
						}
					],
					"request": {
						"method": "GET",
						"header": [
							{
								"key": "Authorization",
								"value": "Bearer {{authToken}}",
								"type": "text"
							}
						],
						"url": {
							"raw": "{{baseUrl}}/batches/program/{{getProgramIdForBatch}}",
							"host": [
								"{{baseUrl}}"
							],
							"path": [
								"batches",
								"program",
								"{{getProgramIdForBatch}}"
							]
						}
					},
					"response": []
				},
				{
					"name": "Create New Batch",
					"event": [
						{
							"listen": "test",
							"script": {
								"exec": [
									"const jsonData = pm.response.json();\r",
									"\r",
									"// Test 1: Status Code\r",
									"pm.test(\"Status code is 201\", function () {\r",
									"    pm.response.to.have.status(201);\r",
									"});\r",
									"\r",
									"\r",
									"    pm.test(\"Batch created successfully\", function () {\r",
									"        pm.expect(jsonData).to.have.property('batchId');\r",
									"        pm.expect(jsonData.batchId).to.be.a('number');\r",
									"    });\r",
									"    \r",
									"    pm.test(\"Response contains all fields\", function () {\r",
									"        pm.expect(jsonData).to.have.property('batchName');\r",
									"        pm.expect(jsonData).to.have.property('batchDescription');\r",
									"        pm.expect(jsonData).to.have.property('batchNoOfClasses');\r",
									"        pm.expect(jsonData).to.have.property('batchStatus');\r",
									"        pm.expect(jsonData).to.have.property('programId');\r",
									"        pm.expect(jsonData).to.have.property('programName');\r",
									"    });\r",
									"    \r",
									"    pm.test(\"Batch ID is auto-generated\", function () {\r",
									"        pm.expect(jsonData.batchId).to.be.greaterThan(0);\r",
									"    });\r",
									"    \r",
									"    pm.test(\"Batch name follows naming convention\", function () {\r",
									"        // Should be: ProgramName + Number(1-99)\r",
									"        const batchName = jsonData.batchName;\r",
									"        const programName = jsonData.programName;\r",
									"        pm.expect(batchName).to.include(programName);\r",
									"    });\r",
									"    \r",
									"    pm.test(\"Description length is valid (4-25 chars)\", function () {\r",
									"        const descLength = jsonData.batchDescription.length;\r",
									"        pm.expect(descLength).to.be.within(4, 25);\r",
									"    });\r",
									"    \r",
									"    // Store created batch ID for further tests\r",
									"    pm.environment.set(\"createdBatchId\", jsonData.batchId);\r",
									"    pm.environment.set(\"createdBatchName\", jsonData.batchName);\r",
									"    \r",
									"    console.log(\"✅ Batch created successfully!\");\r",
									"    console.log(\"Batch ID:\", jsonData.batchId);\r",
									"    console.log(\"Batch Name:\", jsonData.batchName);\r",
									"\r",
									"\r",
									"\r",
									"    \r",
									" \r",
									""
								],
								"type": "text/javascript",
								"packages": {},
								"requests": {}
							}
						}
					],
					"request": {
						"method": "POST",
						"header": [
							{
								"key": "Authorization",
								"value": "Bearer {{authToken}}",
								"type": "text"
							}
						],
						"body": {
							"mode": "raw",
							"raw": "{\r\n  \"batchDescription\": \"{{newBatchDescription}}\",\r\n  \"batchName\": \"{{newBatchName}}\",\r\n  \"batchNoOfClasses\": {{newBatchNoOfClasses}},\r\n  \"batchStatus\": \"{{newBatchStatus}}\",\r\n  \"programId\": {{newProgramId}}\r\n}",
							"options": {
								"raw": {
									"language": "json"
								}
							}
						},
						"url": {
							"raw": "{{baseUrl}}/batches",
							"host": [
								"{{baseUrl}}"
							],
							"path": [
								"batches"
							]
						}
					},
					"response": []
				},
				{
					"name": "Update by Batch ID",
					"event": [
						{
							"listen": "test",
							"script": {
								"exec": [
									"const jsonData = pm.response.json();\r",
									"\r",
									"// Test 1: Status Code\r",
									"pm.test(\"Status code is 200\", function () {\r",
									"    pm.response.to.have.status(200);\r",
									"});\r",
									"\r",
									"\r",
									"    // Test 2: Response structure\r",
									"    pm.test(\"Batch updated successfully\", function () {\r",
									"        pm.expect(jsonData).to.have.property('batchId');\r",
									"    });\r",
									"    \r",
									"    pm.test(\"Response contains all mandatory fields\", function () {\r",
									"        pm.expect(jsonData).to.have.property('batchName');\r",
									"        pm.expect(jsonData).to.have.property('batchDescription');\r",
									"        pm.expect(jsonData).to.have.property('batchStatus');\r",
									"        pm.expect(jsonData).to.have.property('batchNoOfClasses');\r",
									"        pm.expect(jsonData).to.have.property('programId');\r",
									"        pm.expect(jsonData).to.have.property('programName');\r",
									"    });\r",
									"    \r",
									"    \r",
									"    \r",
									"    // 🆕 Test 3: Description was actually CHANGED\r",
									"    pm.test(\"✅ Description was updated (different from original)\", function () {\r",
									"        const originalDesc = pm.environment.get(\"newBatchDescription\");\r",
									"        const updatedDesc = jsonData.batchDescription;\r",
									"        pm.expect(updatedDesc).to.not.eql(originalDesc);\r",
									"    });\r",
									"    \r",
									"    // 🆕 Test 4: Description matches what we sent\r",
									"    pm.test(\"✅ Description matches expected value\", function () {\r",
									"        const expectedDesc = pm.environment.get(\"updatedBatchDescription\");\r",
									"        pm.expect(jsonData.batchDescription).to.eql(expectedDesc);\r",
									"    });\r",
									"    \r",
									"   \r",
									"    \r",
									"    // 🆕 Console: BEFORE vs AFTER comparison\r",
									"    console.log(\"\\n🔄 UPDATE VERIFICATION - BEFORE vs AFTER:\");\r",
									"    console.log(\"=\" .repeat(60));\r",
									"    console.log(\"Batch ID:\", jsonData.batchId, \"(unchanged ✓)\");\r",
									"    console.log(\"\\nDescription:\");\r",
									"    console.log(\"  BEFORE:\", pm.environment.get(\"newBatchDescription\"));\r",
									"    console.log(\"  AFTER: \", jsonData.batchDescription);\r",
									"    console.log(\"  CHANGED:\", pm.environment.get(\"newBatchDescription\") !== jsonData.batchDescription ? \"✅ YES\" : \"❌ NO\");\r",
									"    console.log(\"\\n\" + \"=\" .repeat(60));\r",
									"    console.log(\"✅ Update verified successfully!\");\r",
									"    console.log(\"=\" .repeat(60));\r",
									"\r",
									"\r",
									"\r",
									""
								],
								"type": "text/javascript",
								"packages": {},
								"requests": {}
							}
						}
					],
					"request": {
						"method": "PUT",
						"header": [
							{
								"key": "Authorization",
								"value": "Bearer {{authToken}}",
								"type": "text"
							}
						],
						"body": {
							"mode": "raw",
							"raw": "{\r\n  \"batchDescription\": \"{{updatedBatchDescription}}\",\r\n  \"batchName\": \"{{newBatchName}}\",\r\n  \"batchNoOfClasses\": {{newBatchNoOfClasses}},\r\n  \"batchStatus\": \"{{newBatchStatus}}\",\r\n  \"programId\": {{newProgramId}},\r\n  \"batchId\": {{createdBatchId}}\r\n}",
							"options": {
								"raw": {
									"language": "json"
								}
							}
						},
						"url": {
							"raw": "{{baseUrl}}/batches/{{createdBatchId}}",
							"host": [
								"{{baseUrl}}"
							],
							"path": [
								"batches",
								"{{createdBatchId}}"
							]
						}
					},
					"response": []
				},
				{
					"name": "Delete by Batch ID",
					"event": [
						{
							"listen": "test",
							"script": {
								"exec": [
									"pm.test(\"Status code is 200\", function () {\r",
									"    pm.response.to.have.status(200);\r",
									"});\r",
									"\r",
									"pm.test(\"Deletion success message is correct\", function () {\r",
									"    let responseText = pm.response.text();\r",
									"    pm.expect(responseText).to.include(\"Message: Batch with Id-\");\r",
									"    pm.expect(responseText).to.include(\"deleted Successfully!\");\r",
									"});"
								],
								"type": "text/javascript",
								"packages": {},
								"requests": {}
							}
						}
					],
					"request": {
						"method": "DELETE",
						"header": [
							{
								"key": "Authorization",
								"value": "Bearer {{authToken}}",
								"type": "text"
							}
						],
						"url": {
							"raw": "{{baseUrl}}/batches/{{createdBatchId}}",
							"host": [
								"{{baseUrl}}"
							],
							"path": [
								"batches",
								"{{createdBatchId}}"
							]
						}
					},
					"response": []
				}
			]
		},
		{
			"name": "Negative Tests",
			"item": [
				{
					"name": "Get Batches - Invalid ID",
					"event": [
						{
							"listen": "test",
							"script": {
								"exec": [
									"const response = pm.response.json();\r",
									"\r",
									"\r",
									"pm.test(\"Status code is 404\", function () {\r",
									"    pm.expect(pm.response.code).to.equal(404);\r",
									"});\r",
									"\r",
									"\r",
									"\r",
									"pm.test(\"Response body has expected properties\", function () {\r",
									"    pm.expect(response).to.have.property('message');\r",
									"    pm.expect(response).to.have.property('success');\r",
									"});\r",
									"\r",
									"\r",
									"pm.test(\"Response message is correct\", function () {\r",
									"    pm.expect(response.message).to.include(\"Batch not found with Id\");\r",
									"    pm.expect(response.success).to.be.false;\r",
									"});\r",
									""
								],
								"type": "text/javascript",
								"packages": {}
							}
						}
					],
					"request": {
						"method": "GET",
						"header": [
							{
								"key": "Authorization",
								"value": "Bearer {{authToken}}",
								"type": "text"
							}
						],
						"url": {
							"raw": "{{baseUrl}}/batches/batchId/999",
							"host": [
								"{{baseUrl}}"
							],
							"path": [
								"batches",
								"batchId",
								"999"
							]
						}
					},
					"response": []
				},
				{
					"name": "Get Batches - Negative or Zero ID",
					"event": [
						{
							"listen": "test",
							"script": {
								"exec": [
									"const response = pm.response.json();\r",
									"\r",
									"\r",
									"pm.test(\"Status code is 400\", function () {\r",
									"    pm.expect(pm.response.code).to.equal(400);\r",
									"});\r",
									"\r",
									"pm.test(\"Response body has required fields\", function () {\r",
									"    pm.expect(response).to.have.property('message');\r",
									"    pm.expect(response).to.have.property('success');\r",
									"\r",
									"\r",
									"    pm.expect(response.success).to.be.a('boolean');\r",
									"    pm.expect(response.success).to.equal(false);\r",
									"});\r",
									""
								],
								"type": "text/javascript",
								"packages": {}
							}
						}
					],
					"request": {
						"method": "GET",
						"header": [
							{
								"key": "Authorization",
								"value": "Bearer {{authToken}}",
								"type": "text"
							}
						],
						"url": {
							"raw": "{{baseUrl}}/batches/batchId/0",
							"host": [
								"{{baseUrl}}"
							],
							"path": [
								"batches",
								"batchId",
								"0"
							]
						}
					},
					"response": []
				},
				{
					"name": "Create Batch-Duplicate Name",
					"event": [
						{
							"listen": "test",
							"script": {
								"exec": [
									"pm.test(\"Status code is 400\", function () {\r",
									"    pm.response.to.have.status(400);\r",
									"});\r",
									"\r",
									"const response = pm.response.json();\r",
									"pm.test(\"Response has required fields\", function () {\r",
									"    pm.expect(response).to.have.property('message');\r",
									"    pm.expect(response).to.have.property('success');\r",
									"});\r",
									"\r",
									"pm.test(\"Success field is false for Duplicate Batch Name\", function () {\r",
									"    pm.expect(response.success).to.be.false;\r",
									"});\r",
									"\r",
									"pm.test(\"Error message indicates duplicate or already exists\", function () {\r",
									"    const message = response.message.toLowerCase();\r",
									"    pm.expect(message).to.include('already exists');\r",
									"});\r",
									""
								],
								"type": "text/javascript",
								"packages": {},
								"requests": {}
							}
						}
					],
					"request": {
						"method": "POST",
						"header": [
							{
								"key": "Authorization",
								"value": "Bearer {{authToken}}",
								"type": "text"
							}
						],
						"body": {
							"mode": "raw",
							"raw": "{\r\n    \"batchName\": \"B2CBatch1\",\r\n    \"batchDescription\": \"string\",\r\n    \"batchStatus\": \"Active\",\r\n    \"batchNoOfClasses\": 25,\r\n    \"programId\": 1 \r\n}",
							"options": {
								"raw": {
									"language": "json"
								}
							}
						},
						"url": {
							"raw": "{{baseUrl}}/batches",
							"host": [
								"{{baseUrl}}"
							],
							"path": [
								"batches"
							]
						}
					},
					"response": []
				},
				{
					"name": "Create Batch-Invalid Batch Name",
					"event": [
						{
							"listen": "test",
							"script": {
								"exec": [
									"const response = pm.response.json();\r",
									"\r",
									"\r",
									"pm.test(\"Status code is 400\", function () {\r",
									"    pm.expect(pm.response.code).to.equal(400);\r",
									"});\r",
									"\r",
									"\r",
									"pm.test(\"Success flag is false\", function () {\r",
									"    pm.expect(response.success).to.be.false;\r",
									"});\r",
									"\r",
									"\r",
									"pm.test(\"Message field exists\", function () {\r",
									"    pm.expect(response.message).to.exist;\r",
									"});\r",
									"\r",
									"\r",
									"\r",
									""
								],
								"type": "text/javascript",
								"packages": {}
							}
						}
					],
					"request": {
						"method": "POST",
						"header": [
							{
								"key": "Authorization",
								"value": "Bearer {{authToken}}",
								"type": "text"
							}
						],
						"body": {
							"mode": "raw",
							"raw": "{\r\n  \"batchDescription\": \"Invalid name\",\r\n  \"batchName\": \"SDET@1\",  \r\n  \"batchNoOfClasses\": 25,\r\n  \"batchStatus\": \"Active\",\r\n  \"programId\": 1\r\n}",
							"options": {
								"raw": {
									"language": "json"
								}
							}
						},
						"url": {
							"raw": "{{baseUrl}}/batches",
							"host": [
								"{{baseUrl}}"
							],
							"path": [
								"batches"
							]
						}
					},
					"response": []
				},
				{
					"name": "Create Batch-Missing Batch Name",
					"event": [
						{
							"listen": "test",
							"script": {
								"exec": [
									"pm.test(\"Status code is 400\", function () {\r",
									"    pm.response.to.have.status(400);\r",
									"});\r",
									"\r",
									"const response = pm.response.json();\r",
									"pm.test(\"Response has required fields\", function () {\r",
									"    pm.expect(response).to.have.property('message');\r",
									"    pm.expect(response).to.have.property('success');\r",
									"});\r",
									"\r",
									"pm.test(\"Success field is false for Missing Batch Name\", function () {\r",
									"    pm.expect(response.success).to.be.false;\r",
									"});\r",
									"\r",
									"pm.test(\"Error message indicates Missing batch name\", function () {\r",
									"    const message = response.message;\r",
									"    pm.expect(message).to.include('Batch Name is mandatory');\r",
									"});\r",
									""
								],
								"type": "text/javascript",
								"packages": {},
								"requests": {}
							}
						}
					],
					"request": {
						"method": "POST",
						"header": [
							{
								"key": "Authorization",
								"value": "Bearer {{authToken}}",
								"type": "text"
							}
						],
						"body": {
							"mode": "raw",
							"raw": "{\r\n    \"batchDescription\": \"newbatchdescription\",\r\n    \"batchStatus\": \"Active\",\r\n    \"batchNoOfClasses\": 25,\r\n    \"programId\": 1 \r\n}",
							"options": {
								"raw": {
									"language": "json"
								}
							}
						},
						"url": {
							"raw": "{{baseUrl}}/batches",
							"host": [
								"{{baseUrl}}"
							],
							"path": [
								"batches"
							]
						}
					},
					"response": []
				},
				{
					"name": "Create Batch-Missing Program ID",
					"event": [
						{
							"listen": "test",
							"script": {
								"exec": [
									"const response = pm.response.json();\r",
									"\r",
									"pm.test(\"Status code is 400\", function () {\r",
									"    pm.expect(pm.response.code).to.equal(400);\r",
									"});\r",
									"\r",
									"\r",
									"pm.test(\"Success is false\", function () {\r",
									"    pm.expect(response.success).to.be.false;\r",
									"});\r",
									"\r",
									"\r",
									"pm.test(\"Message contains 'ProgramId field is needed'\", function () {\r",
									"    pm.expect(response.message).to.include(\"ProgramId field is needed\");\r",
									"});\r",
									""
								],
								"type": "text/javascript",
								"packages": {}
							}
						}
					],
					"request": {
						"method": "POST",
						"header": [
							{
								"key": "Authorization",
								"value": "Bearer {{authToken}}",
								"type": "text"
							}
						],
						"body": {
							"mode": "raw",
							"raw": "{\r\n  \"batchDescription\": \"Automation batch\",\r\n  \"batchName\": \"SDET221\",\r\n  \"batchNoOfClasses\": 25,\r\n  \"batchStatus\": \"Active\"\r\n }",
							"options": {
								"raw": {
									"language": "json"
								}
							}
						},
						"url": {
							"raw": "{{baseUrl}}/batches",
							"host": [
								"{{baseUrl}}"
							],
							"path": [
								"batches"
							]
						}
					},
					"response": []
				},
				{
					"name": "Create Batch-Invalid Program ID",
					"event": [
						{
							"listen": "test",
							"script": {
								"exec": [
									"const response = pm.response.json();\r",
									"\r",
									"\r",
									"pm.test(\"Status code is 404\", function () {\r",
									"    pm.expect(pm.response.code).to.equal(404);\r",
									"});\r",
									"\r",
									"\r",
									"pm.test(\"Response body contains message and success fields\", function () {\r",
									"    pm.expect(response).to.have.all.keys('message', 'success');\r",
									"});\r",
									"\r",
									"\r",
									"pm.test(\"Success field is a boolean\", function () {\r",
									"    pm.expect(response.success).to.be.a('boolean');\r",
									"});\r",
									""
								],
								"type": "text/javascript",
								"packages": {}
							}
						}
					],
					"request": {
						"method": "POST",
						"header": [
							{
								"key": "Authorization",
								"value": "Bearer {{authToken}}",
								"type": "text"
							}
						],
						"body": {
							"mode": "raw",
							"raw": "{\r\n  \"batchDescription\": \"Automation batch\",\r\n  \"batchName\": \"SDET221\",\r\n  \"batchNoOfClasses\": 25,\r\n  \"batchStatus\": \"Active\",\r\n  \"programId\": 9999\r\n }",
							"options": {
								"raw": {
									"language": "json"
								}
							}
						},
						"url": {
							"raw": "{{baseUrl}}/batches",
							"host": [
								"{{baseUrl}}"
							],
							"path": [
								"batches"
							]
						}
					},
					"response": []
				},
				{
					"name": "Create Batch-Missing Batch Status",
					"event": [
						{
							"listen": "test",
							"script": {
								"exec": [
									"const response = pm.response.json();\r",
									"\r",
									"\r",
									"pm.test(\"Status code is 400\", function () {\r",
									"    pm.expect(pm.response.code).to.equal(400);\r",
									"});\r",
									"\r",
									"\r",
									"pm.test(\"Response has success field\", function () {\r",
									"    pm.expect(response).to.have.property('success');\r",
									"    pm.expect(response.success).to.be.a('boolean');\r",
									"});\r",
									"\r",
									"\r",
									"pm.test(\"Response has message field\", function () {\r",
									"    pm.expect(response).to.have.property('message');\r",
									"    pm.expect(response.message).to.be.a('string');\r",
									"});\r",
									""
								],
								"type": "text/javascript",
								"packages": {}
							}
						}
					],
					"request": {
						"method": "POST",
						"header": [
							{
								"key": "Authorization",
								"value": "Bearer {{authToken}}",
								"type": "text"
							}
						],
						"body": {
							"mode": "raw",
							"raw": "{\r\n  \"batchDescription\": \"Duplicate Automation batch\",\r\n  \"batchName\": \"SDET226\",\r\n  \"batchNoOfClasses\": 25,\r\n  \"programId\": 3\r\n}",
							"options": {
								"raw": {
									"language": "json"
								}
							}
						},
						"url": {
							"raw": "{{baseUrl}}/batches",
							"host": [
								"{{baseUrl}}"
							],
							"path": [
								"batches"
							]
						}
					},
					"response": []
				},
				{
					"name": "Create Batch-Missing No of Classes",
					"event": [
						{
							"listen": "test",
							"script": {
								"exec": [
									"const response = pm.response.json();\r",
									"\r",
									"\r",
									"pm.test(\"Status code is 400\", function () {\r",
									"    pm.expect(pm.response.code).to.equal(400);\r",
									"});\r",
									"\r",
									"\r",
									"pm.test(\"Success field is false\", function () {\r",
									"    pm.expect(response.success).to.equal(false);\r",
									"});\r",
									"\r",
									""
								],
								"type": "text/javascript",
								"packages": {}
							}
						}
					],
					"request": {
						"method": "POST",
						"header": [
							{
								"key": "Authorization",
								"value": "Bearer {{authToken}}",
								"type": "text"
							}
						],
						"body": {
							"mode": "raw",
							"raw": "{\r\n  \"batchDescription\": \"Duplicate Automation batch\",\r\n  \"batchName\": \"SDET226\",\r\n  \"batchStatus\": \"Active\",\r\n  \"programId\": 3\r\n}",
							"options": {
								"raw": {
									"language": "json"
								}
							}
						},
						"url": {
							"raw": "{{baseUrl}}/batches",
							"host": [
								"{{baseUrl}}"
							],
							"path": [
								"batches"
							]
						}
					},
					"response": []
				},
				{
					"name": "Create Batch Description-less than4 char",
					"event": [
						{
							"listen": "test",
							"script": {
								"exec": [
									"pm.test(\"Status code is 400\", function () {\r",
									"    pm.response.to.have.status(400);\r",
									"});\r",
									"\r",
									"let json = pm.response.json();\r",
									"pm.test(\"Response has required fields\", function () {\r",
									"    pm.expect(response).to.have.property('message');\r",
									"    pm.expect(response).to.have.property('success');\r",
									"});\r",
									"\r",
									"pm.test(\"Success field is false for Program description length too short\", function () {\r",
									"    pm.expect(response.success).to.be.false;\r",
									"});\r",
									"\r",
									"pm.test(\"Error message indicates description length\", function () {\r",
									"    pm.expect(pm.response.text()).to.include('min length 4');\r",
									"});"
								],
								"type": "text/javascript",
								"packages": {},
								"requests": {}
							}
						}
					],
					"request": {
						"method": "POST",
						"header": [
							{
								"key": "Authorization",
								"value": "Bearer {{authToken}}",
								"type": "text"
							}
						],
						"body": {
							"mode": "raw",
							"raw": "{\r\n  \"batchDescription\": \"abc\",\r\n  \"batchName\": \"{{newBatchName4DescShort}}\",\r\n  \"batchNoOfClasses\": 20,\r\n  \"batchStatus\": \"Active\",\r\n  \"programId\": 1\r\n}",
							"options": {
								"raw": {
									"language": "json"
								}
							}
						},
						"url": {
							"raw": "{{baseUrl}}/batches",
							"host": [
								"{{baseUrl}}"
							],
							"path": [
								"batches"
							]
						}
					},
					"response": []
				},
				{
					"name": "Create Batch Description-more than 25 char Copy",
					"event": [
						{
							"listen": "test",
							"script": {
								"exec": [
									"pm.test(\"Status code is 400\", function () {\r",
									"    pm.response.to.have.status(400);\r",
									"});\r",
									"\r",
									"let json = pm.response.json();\r",
									"pm.test(\"Response has required fields\", function () {\r",
									"    pm.expect(response).to.have.property('message');\r",
									"    pm.expect(response).to.have.property('success');\r",
									"});\r",
									"\r",
									"pm.test(\"Success field is false for Program description length too long\", function () {\r",
									"    pm.expect(response.success).to.be.false;\r",
									"});\r",
									"\r",
									"pm.test(\"Error message indicates description length\", function () {\r",
									"    pm.expect(pm.response.text()).to.include('max length 25');\r",
									"});"
								],
								"type": "text/javascript",
								"packages": {},
								"requests": {}
							}
						}
					],
					"request": {
						"method": "POST",
						"header": [
							{
								"key": "Authorization",
								"value": "Bearer {{authToken}}",
								"type": "text"
							}
						],
						"body": {
							"mode": "raw",
							"raw": "{\r\n  \"batchDescription\": \"ThisIsAVeryLongDescriptionExceedingTwentyFiveCharactersLimit\",\r\n  \"batchName\": \"{{newBatchName4DescLong}}\",\r\n  \"batchNoOfClasses\": 25,\r\n  \"batchStatus\": \"Active\",\r\n  \"programId\": 1\r\n}",
							"options": {
								"raw": {
									"language": "json"
								}
							}
						},
						"url": {
							"raw": "{{baseUrl}}/batches",
							"host": [
								"{{baseUrl}}"
							],
							"path": [
								"batches"
							]
						}
					},
					"response": []
				},
				{
					"name": "Update with Invalid Batch ID",
					"event": [
						{
							"listen": "test",
							"script": {
								"exec": [
									"const response = pm.response.json();\r",
									"\r",
									"pm.test(\"Status code is 404\", function () {\r",
									"    pm.expect(pm.response.code).to.equal(404);\r",
									"});\r",
									"\r",
									"\r",
									"pm.test(\"Response body has expected properties\", function () {\r",
									"    pm.expect(response).to.have.property(\"message\");\r",
									"    pm.expect(response).to.have.property(\"success\");\r",
									"});\r",
									"\r",
									""
								],
								"type": "text/javascript",
								"packages": {}
							}
						}
					],
					"request": {
						"method": "PUT",
						"header": [
							{
								"key": "Authorization",
								"value": "Bearer {{authToken}}",
								"type": "text"
							}
						],
						"body": {
							"mode": "raw",
							"raw": "{\r\n\"batchDescription\": \"SDET TOPPERS\",   \r\n\"batchName\": \"B2CBatch\",\r\n\"batchNoOfClasses\": 59,\r\n\"batchStatus\": \"INACTIVE\",\r\n\"programId\": 3,\r\n\"programName\": \"Testing1\"\r\n}",
							"options": {
								"raw": {
									"language": "json"
								}
							}
						},
						"url": {
							"raw": "{{baseUrl}}/batches/999",
							"host": [
								"{{baseUrl}}"
							],
							"path": [
								"batches",
								"999"
							]
						}
					},
					"response": []
				},
				{
					"name": "Delete with Invalid Batch ID",
					"event": [
						{
							"listen": "test",
							"script": {
								"exec": [
									"const response = pm.response.json();\r",
									"\r",
									"\r",
									"pm.test(\"Status code is 404\", function () {\r",
									"    pm.expect(pm.response.code).to.equal(404);\r",
									"});\r",
									"\r",
									"\r",
									"pm.test(\"Response body has expected properties\", function () {\r",
									"    pm.expect(response).to.have.all.keys('message', 'success');\r",
									"});\r",
									"\r",
									"\r",
									"pm.test(\"'success' field is false\", function () {\r",
									"    pm.expect(response.success).to.equal(false);\r",
									"});\r",
									"\r",
									"\r",
									"pm.test(\"'message' field contains expected text\", function () {\r",
									"    pm.expect(response.message).to.include(\"Batch id not found or not exists\");\r",
									"});\r",
									""
								],
								"type": "text/javascript",
								"packages": {}
							}
						}
					],
					"request": {
						"method": "DELETE",
						"header": [
							{
								"key": "Authorization",
								"value": "Bearer {{authToken}}",
								"type": "text"
							}
						],
						"url": {
							"raw": "{{baseUrl}}/batches/9999",
							"host": [
								"{{baseUrl}}"
							],
							"path": [
								"batches",
								"9999"
							]
						}
					},
					"response": []
				}
			]
		}
	],
	"auth": {
		"type": "bearer",
		"bearer": [
			{
				"key": "token",
				"value": "",
				"type": "string"
			}
		]
	},
	"event": [
		{
			"listen": "prerequest",
			"script": {
				"type": "text/javascript",
				"packages": {},
				"exec": [
					""
				]
			}
		},
		{
			"listen": "test",
			"script": {
				"type": "text/javascript",
				"packages": {},
				"exec": [
					""
				]
			}
		}
	],
	"variable": [
		{
			"key": "authToken",
			"value": ""
		}
	]
}